{
  "base": 34.61601802221121,
  "summary": {
    "30.593849534456613": "In summary : A",
    "30.131310879584753": "In summary : The",
    "30.1308043129248": "In summary : Here's the",
    "31.86721614252217": "The summary : A",
    "30.15325084506781": "In summary , The",
    "29.684007496969134": [
      "",
      "In summary ,"
    ],
    "34.830439660385636": "Read the full summary here A",
    "34.44460470257893": "Read the full summary here The",
    "30.691372725438335": [
      "",
      "The summary :"
    ],
    "29.38622539590493": [
      "",
      "In summary :"
    ],
    "31.251890511714873": [
      "",
      "Full summary :"
    ],
    "30.983342036558334": [
      "",
      "A summary :"
    ],
    "30.454654037941143": "In summary : Read the full",
    "34.50067675974495": "Read the full summary here Full",
    "32.73294097433159": "Read the full summary of this story here The",
    "33.07676437705822": "Read the full summary of this story here A",
    "32.083459943723355": "News summary : A",
    "30.64260491328258": [
      "",
      "News summary :"
    ],
    "32.157901753316615": [
      "",
      "Article summary :"
    ],
    "28.909528268958532": [
      "",
      " In summary ,"
    ],
    "32.76619939655559": "Full summary : A",
    "32.61065335122553": "Here is the summary of what happened A",
    "31.431275182813124": [
      "",
      "website summary :"
    ],
    "30.1097319467482": "So in summary , In",
    "30.120488987127025": "In summary , So in",
    "30.576553581910073": "In summary : News",
    "30.74066191654994": "In summary : Read the",
    "29.89316199020001": [
      "What do you think",
      "In summary ,"
    ],
    "29.790558507152927": [
      "What do you think",
      "In summary :"
    ],
    "28.742253196898268": [
      "What do you think about this",
      "In summary ,"
    ],
    "31.319975382683957": "The summary : In",
    "30.498312143680522": "In summary , A",
    "28.667967384357997": [
      ":",
      " In summary ,"
    ],
    "31.16117234187697": "Here's the summary : In",
    "30.31436846236008": "In summary : So, in",
    "29.516291243268164": "So, in summary : In",
    "32.42812584327471": "The summary is that In",
    "30.954123956910692": "In summary : Executive",
    "31.51810640406343": [
      "",
      "Read the full summary :"
    ],
    "31.902068634469845": [
      "",
      "Read the summary :"
    ],
    "32.69595855492561": "Read the full summary of this incident here A",
    "29.512871384366637": "In summary : Here is the",
    "31.685610011735896": "Here's the summary : A",
    "30.24646364201152": "In summary : So in",
    "30.130232533112313": "In summary : Here\u2019s the",
    "32.838445432668316": "Read the full summary of this story here Full",
    "29.956637142484144": "So in summary : In",
    "30.008255897920115": "In summary , This",
    "34.26003341260308": "Article summary : Executive",
    "30.13470600292137": "In summary : This",
    "31.023329637564732": [
      "",
      "Executive summary :"
    ],
    "33.309921689823874": "Executive summary : Project",
    "31.323467860479795": "In summary : Project",
    "29.834250976219163": [
      "!",
      "In summary :"
    ],
    "31.43982539585266": "Here\u2019s the summary : In",
    "28.94735880122133": "In summary , This is the",
    "33.00373106904744": "Recipe summary : In",
    "32.87624920015788": "In summary : Recipe",
    "35.22961178262406": "Read the summary here The",
    "31.15226346676879": "A summary of the results can be found here The",
    "30.9265425025316": [
      "",
      "Video summary :"
    ],
    "30.807628743424814": "A summary of the incident can be found here Full",
    "30.965039796733112": "A summary of the incident can be found here The",
    "30.206521315036657": "A summary of the incident can be found here In",
    "33.64717388263278": "See the summary below for more information The",
    "33.88928372388695": "The summary is below See the full",
    "32.93269009445507": [
      "",
      "crime summary :"
    ],
    "30.537240070647698": [
      "",
      "news summary :"
    ],
    "31.6117212754062": "A summary of the charges can be found here The",
    "31.1080504301394": "A summary of the case can be found here The",
    "29.429941673976188": [
      ":",
      "In summary ,"
    ],
    "31.861582678166403": "Short summary : In",
    "29.10977571916521": "In summary : This is the",
    "31.066146029788836": [
      "",
      "Short summary :"
    ],
    "32.660429813812954": "Short summary : Full",
    "30.70272500254937": "In summary : Short",
    "30.224692507198977": [
      "How are you",
      "In summary ,"
    ],
    "29.940782020048374": [
      "How are you doing",
      "In summary ,"
    ],
    "29.07240704713211": "In summary , This is a",
    "30.010578079393035": "In summary , in",
    "29.74322876905553": "in summary , In",
    "33.19314449614366": [
      "\"",
      "Read the full summary here"
    ],
    "29.254830860739293": " In summary , in",
    "31.11234903006057": "A summary of the report can be found here The",
    "31.88490759514658": "Brief summary : In",
    "30.318718416266307": "A summary of the case can be found here In",
    "28.528387614593182": [
      "",
      " In summary :"
    ],
    "31.42164219510333": "A summary of the investigation can be found here The",
    "29.4105811268621": [
      "1",
      "In summary ,"
    ],
    "29.892133473525433": "in summary : In",
    "30.003629637937216": [
      "!",
      "In summary ,"
    ],
    "30.110746124955874": [
      "",
      " summary :"
    ],
    "32.03231177377358": "website summary : web site",
    "27.963829200596578": [
      ":",
      "! In summary ,"
    ],
    "30.5755732393426": "A summary of the investigation can be found here In",
    "29.559342595610435": "In summary : in",
    "32.17254421248074": "Executive summary : executive",
    "32.73710052635326": "A summary of the charges is below The",
    "30.63629895475915": "In summary , Read the full",
    "34.29164672253649": "Read the full summary here In",
    "32.77258847184277": "Story summary : News",
    "33.62889518310184": "Read the full summary of this story Full",
    "31.947136108517906": [
      "",
      "A summary of what happened:"
    ],
    "30.591968511902163": "A summary of the incident can be found here News",
    "28.15794164599046": [
      "",
      "! In summary ,"
    ],
    "28.349561999238393": [
      "",
      "! In summary :"
    ],
    "28.636715994801023": "! In summary , The",
    "35.25333188567866": "See the summary below The",
    "29.911545496139695": [
      ")",
      "In summary ,"
    ],
    "29.174120080755213": [
      "!",
      " In summary ,"
    ],
    "28.647643639536124": " In summary :, in",
    "27.554077465554503": "! In summary :, thanks for the",
    "34.13660119750123": "Read the full summary here See",
    "32.07196490290171": "A summary of the figures can be found here The",
    "31.61363105859305": "A summary of the proceedings can be found here The",
    "31.843021470776097": "Executive summary : In",
    "30.34725634223667": "In summary : Here\u2019s a"
  },
  "sum up": {
    "30.472073246204644": "To sum up : \"To",
    "31.074542176348974": "To sum up : Let\u2019s",
    "30.331649218913558": "So to sum up : To",
    "31.106341596155755": "To sum up : So to",
    "30.821523659877442": "To sum up : How to",
    "30.648393605293375": "To sum up : Let's",
    "28.508078691372393": [
      "",
      "to sum up ,"
    ],
    "31.004598593812084": "To sum up : How do you",
    "30.92514208369781": "\"To sum up : To",
    "29.581481009674484": "To sum up : Here is how to",
    "29.89583193529516": [
      "",
      "To sum up ,"
    ],
    "30.121186861002727": "So to sum up , To",
    "31.12442673454931": "To sum up : How would you",
    "29.821291481391853": [
      "",
      "To sum up :"
    ],
    "29.882869433831765": "So, to sum up : To",
    "30.83336504242235": "To sum up : So, to",
    "31.762822216296843": "Let\u2019s sum up : To",
    "29.90309397762863": "To sum up : Here's how to",
    "30.204711401717763": [
      "!",
      "To sum up :"
    ],
    "30.730825877215096": "To sum up , So to",
    "30.512092794335693": "In sum up , To",
    "30.20936383012673": "To sum up : Here\u2019s how to",
    "28.60681775220333": [
      "",
      "! To sum up ,"
    ],
    "29.2826146200666": [
      "",
      " To sum up ,"
    ],
    "30.151944953235166": [
      "\"",
      "To sum up :"
    ],
    "29.66206185207305": "To sum up : This will",
    "31.57325073668542": "Let's sum up : To",
    "30.18144403518949": "To sum up , to",
    "29.561975342963393": " To sum up , to",
    "30.517739751591108": "To sum up : \"It's hard to",
    "29.930492772940696": "To sum up : Click here to",
    "29.973916951574555": "To sum up : Here we",
    "30.151924074652097": "To sum up : That should",
    "30.47868759194249": "\"To sum up , To",
    "30.284726636303052": "To sum up , \"To",
    "30.2184299621331": "To sum up : \"I can't",
    "30.263909890322537": "To sum up : We",
    "30.06057224143384": [
      "What do you think",
      "To sum up ,"
    ],
    "29.96332214987705": "To sum up , Let me",
    "31.375374939055593": "Let me sum up : To",
    "30.04779773711658": "To sum up : Let me",
    "30.046042167181792": "To sum up : I'll",
    "30.876591173749244": "Just to sum up : To",
    "30.758556603109056": "To sum up , Person3: Let me",
    "30.778480784842813": "To sum up : These tips",
    "29.00173584439644": "! So to sum up , To",
    "29.89313327960287": " So to sum up ,! To",
    "29.505414396354936": "! To sum up , So to",
    "30.334804260546996": " To sum up ,! So to",
    "30.027031219458014": "To sum up : to",
    "30.03893503556532": [
      ")",
      "To sum up :"
    ],
    "29.699833898692045": [
      "\u2013",
      "To sum up :"
    ],
    "30.002216910426753": "To sum up : This should",
    "31.836925537477896": "How would you sum up this story? Please",
    "31.153769121182425": "How would you sum up this story? We'll",
    "30.27640856566276": [
      "'",
      "To sum up :"
    ],
    "31.470259546269663": "To sum up , The following sentences",
    "32.36884434370837": "To sum up the story, So to",
    "29.48097486314915": "To sum up , In order to",
    "30.914336046859017": "To sum up the story, In order to",
    "30.704218319019912": "To sum up , Let's",
    "31.05862432920139": "Just to sum up , To",
    "31.274200782934493": [
      "",
      "To sum up the conversation,"
    ],
    "28.76373998312802": [
      "",
      "! To sum up :"
    ],
    "29.32490262820287": " To sum up : to",
    "29.837856865744673": [
      "and",
      "To sum up :"
    ],
    "29.749298492552043": "to sum up : To",
    "30.05096253851224": [
      "Fire and",
      "To sum up :"
    ],
    "29.987888410377852": "To sum up : Here are the steps to",
    "29.807103810612993": [
      "Mr",
      "To sum up :"
    ],
    "30.11197021878818": "To sum up : I can't",
    "32.407026378759205": "How would you sum up this story? To",
    "30.9240734196887": [
      "!",
      "that would sum up the game for me"
    ],
    "30.89228330748024": [
      "",
      "that would sum up the game!"
    ],
    "30.655674449670006": [
      "The body of",
      "To sum up :"
    ],
    "29.953726859096175": "To sum up : \"It is hard to",
    "29.450705935822832": "to sum up , To",
    "30.149265837045654": [
      "What do you think",
      "To sum up :"
    ],
    "32.36371013121165": "To sum up the episode, So to",
    "29.76876306783994": [
      "",
      "can sum up :"
    ],
    "29.583679622771125": [
      "2",
      "To sum up :"
    ],
    "30.03000206346864": [
      "3",
      "To sum up :"
    ],
    "31.945741877469054": "How would you sum up this story? We\u2019ll",
    "29.829734547447742": "To sum up , Let us",
    "31.555757453702405": "To sum up the conversation, Let me",
    "31.508581956229044": "To sum up the story, Let me",
    "29.574303576118822": [
      "1",
      "To sum up :"
    ],
    "29.867136854444613": "To sum up : Here are some tips to",
    "29.82949986365502": " To sum up : can",
    "28.994635260665397": [
      ":",
      " To sum up ,"
    ],
    "28.995731927722172": [
      "",
      "to sum up :"
    ],
    "30.072113656177446": " To sum up : How to",
    "31.614000510145917": "How to sum up : To",
    "30.619525359592267": [
      "The",
      "To sum up :"
    ],
    "30.493782407488485": "To sum up , follow these steps This should",
    "30.000904558713415": "To sum up , follow the steps below This should",
    "31.287665269362062": "To sum up : The following steps",
    "30.65905155043911": [
      "",
      "To sum up "
    ],
    "29.49543835865101": [
      "!",
      "So, to sum up :"
    ],
    "31.534850597722286": "How would you sum up this story? You can",
    "30.23035754299968": [
      "What is your name",
      "To sum up ,"
    ],
    "29.949691824822697": "To sum up , In",
    "30.525383533010896": [
      "",
      "Person3: To sum up ,"
    ],
    "29.959617287311122": [
      "4",
      "To sum up :"
    ],
    "29.84328532600775": [
      "'s",
      "To sum up :"
    ],
    "30.11487343445241": "To sum up : It will",
    "31.985634626760884": "The sum up : To",
    "30.463184293418674": "To sum up : The",
    "29.107474505830353": "To sum up : Here are some tips to help you",
    "29.852903948360595": "To sum up : \"It really does",
    "29.935716309595822": [
      ",",
      "To sum up :"
    ],
    "29.53699398436338": "To sum up : \"I think that would",
    "29.768458104260763": [
      "",
      "To sum up , the"
    ],
    "30.477891301117623": "To sum up , Just to",
    "30.750881692386585": "To sum up , Let\u2019s",
    "33.474729819617274": "Let's sum up  To",
    "30.151907874839086": "To sum up : That seems to",
    "30.62201753321281": "To sum up : \"It's difficult to",
    "29.887050875392735": [
      "!",
      "So to sum up :"
    ],
    "32.952974622179475": "Let me sum up  To",
    "29.574795097352258": " So to sum up , To",
    "30.940488941910743": [
      "",
      "How would you sum up this story?"
    ],
    "31.011399775977868": "To sum up : Click OK to",
    "30.357051439786748": "To sum up : They",
    "31.19585904759709": [
      "",
      "To sum up the story,"
    ],
    "28.992820406384052": "To sum up , I think that would",
    "29.356071715781674": [
      "metallic heels are the perfect choice for your evening look!",
      "To sum up , try something new"
    ],
    "29.18771470978824": [
      "metallic heels are the perfect choice for your evening look!",
      "To sum up , try something different"
    ],
    "29.05096171985372": [
      "metallic heels are the perfect choice for your evening look!",
      "To sum up :"
    ],
    "28.47033154247707": [
      "metallic heels are the perfect choice for your evening look!",
      "To sum up , consider these tips"
    ],
    "28.80502053577569": [
      "metallic heels are the perfect choice for your evening look!",
      "To sum up , try these tips"
    ],
    "30.749483235733248": "To sum up , here are some tips to help you make the most of your cocktail dress",
    "30.41260797745703": "To sum up : \"They",
    "30.53429845990413": [
      "!",
      "To sum up this article:"
    ],
    "30.40750926168118": "To sum up : One word to",
    "30.966743960118293": "To sum up : One word can",
    "30.827607634023668": "To sum up : How do we",
    "30.022927673471763": "To sum up : \"It will",
    "30.092233141531274": [
      ")",
      "To sum up ,"
    ],
    "28.773359161139144": "To sum up , I want to",
    "31.676492637983987": "To sum up the story, Well to",
    "32.32477872205261": "To sum up the conversation, So to",
    "30.562401877925907": "To sum up , That would",
    "31.1482186135253": [
      "",
      "To sum up the interview,"
    ],
    "28.41789220293773": "To sum up : This is the perfect way to",
    "30.935610814698244": "To sum up : How do I",
    "31.297531447411128": [
      "The",
      "To sum up the situation:"
    ],
    "31.147987695121998": "To sum up : Click \"OK\" to",
    "29.74888095871595": "To sum up : Here is a"
  },
  "main idea": {
    "31.099864313723838": "This is the main idea  The",
    "31.5413228374349": "That was the main idea  The",
    "32.028113610672975": "This is the main idea of this story The",
    "32.638908261298994": [
      "",
      "The main idea is that"
    ],
    "31.20911320590853": "Remember the main idea : The",
    "33.11228158210483": "But the main idea is that The",
    "33.553936827968336": "The main idea is that But the",
    "31.490550996822414": "Here\u2019s the main idea : The",
    "31.036640499536254": "The main idea : This is the",
    "33.13773608945693": "That\u2019s the main idea  The",
    "30.691360243947784": "The main idea of this story is that That was the",
    "31.715055252463973": "This is the main idea of this article The",
    "31.331277675574867": "The main idea of this story is that This",
    "31.513401447650594": [
      "",
      "The main idea :"
    ],
    "31.351566360950603": [
      "",
      "The main idea of this story is that"
    ],
    "32.559984466165346": [
      "",
      "The main idea is simple:"
    ],
    "32.779037011451315": "The main idea is this: Remember the",
    "32.027651332967096": "The main idea : \"The",
    "31.591803048544666": [
      "",
      "The main idea of the story is that"
    ],
    "32.24021997702045": "That's the main idea  The",
    "31.235818093421223": "Here's the main idea : The",
    "31.812545578634577": [
      "",
      "The main idea ?"
    ],
    "31.71030483510704": "That is the main idea  The",
    "32.98132028647696": [
      "",
      "The main idea was that"
    ],
    "33.3769936805632": "The main idea is that \"The",
    "31.843201659881988": "The main idea of this story is that So the",
    "34.46384414247482": "That's the main idea here The",
    "32.07550073427308": "The main idea is that That was the",
    "31.885454870560203": "The main idea was that This is the",
    "31.610270611518505": "The main idea of this story is that In the",
    "30.230653592642867": "The main idea of this story is that This was the",
    "32.69019583411625": "Here's the main idea  The",
    "32.147543728824296": "The main idea of this story is that Our",
    "29.539760175218124": [
      "",
      "\"This is the main idea \""
    ],
    "30.22672706060899": "This is the main idea of this article: The",
    "33.574673024204436": "\"The main idea is to save money\" The",
    "32.749834178819874": [
      "",
      "The main idea here is that"
    ],
    "32.00412618260454": "The main idea of this story is that My",
    "32.689126748656115": [
      "What do you think",
      "The main idea is that"
    ],
    "31.893484611623816": "The main idea of this story is that So, the",
    "27.859271699385257": [
      "",
      ", that was the main idea "
    ],
    "31.708667914908375": "The main idea : That's the",
    "32.84618638386032": "The main idea is simple: That's the",
    "30.057864655789558": "! The main idea of this story is that So the",
    "33.394736122397106": "The main idea is simple That's the",
    "31.868685347417884": "Our main idea : The",
    "32.4138499582705": "Your main idea : The",
    "32.99642199934206": "The main idea : Your",
    "30.56480824114112": "Here is the main idea : The",
    "30.249748603671705": [
      "",
      " The main idea of this story is that"
    ],
    "31.956506000863524": "The main idea : But the",
    "32.19049130283069": "This is the main idea of this game The",
    "33.299615533574325": "This is the main idea here The",
    "30.25329219102956": "The main idea of this story is that I think the",
    "31.350909826236894": "Remember the main idea ? The",
    "33.10340987011591": "The main idea is simple: Remember the",
    "33.277388615123826": [
      "",
      "The main idea is simple"
    ],
    "32.35393059595131": [
      "",
      "The main idea is this:"
    ],
    "29.944849831557864": "This is the main idea : The",
    "31.678800028850475": [
      ":",
      "The main idea of this episode is that"
    ],
    "33.01150059058933": "So the main idea is that The",
    "31.65426826630809": "I think the main idea is that The",
    "32.84083109547458": [
      "!",
      "The main idea is simple:"
    ],
    "33.60452652401248": [
      "!",
      "The main idea is simple"
    ],
    "31.77114143625212": "The main idea : Remember the",
    "34.17614549517239": "The main idea is simple: Your",
    "30.45488271933265": [
      "",
      "That was the main idea "
    ],
    "32.87129468107878": "This is the main idea of this tutorial The",
    "33.799469020721965": "This is the main idea of this recipe The",
    "32.300508990206495": [
      "!",
      "That's the main idea of this story"
    ],
    "32.25091633617619": [
      "!",
      "That's the main idea of this post"
    ],
    "31.230186814183504": "The main idea of this story is that That's the",
    "33.145927003984205": "That's the main idea of this story The",
    "30.525711613617823": [
      "",
      " The main idea of the story is that"
    ],
    "31.58988442135553": [
      "",
      " The main idea is that"
    ],
    "30.22847342923921": [
      ":",
      " The main idea of the story is that"
    ],
    "30.457392148231577": " The main idea of this story is that the",
    "31.13440976023759": "The main idea : Here is the",
    "32.02047729181028": "Here is the main idea  The",
    "32.625271222915345": "The main idea ? \"The",
    "30.918784260827305": "This is the main idea  \"The",
    "33.5450312599885": "The main idea is simple Remember the",
    "32.581048923065644": "The main idea is that That's the",
    "32.625178959252665": "The main idea here is that That's the",
    "31.264562394169012": "The main idea behind the sale was to raise money for charity \"The",
    "31.362708729702618": "The main idea behind the auction was to raise money for charity \"The",
    "32.361308227669376": "\"The main idea is to get rid of it\" The",
    "30.976674422966155": "The main idea : This is my",
    "32.6732986035733": "This is the main idea behind it The",
    "31.94012303362236": "This is the main idea behind this project The",
    "31.543414382312996": "This is the main idea of this project The",
    "30.791183982858275": [
      "",
      "The main idea of this article is:"
    ],
    "31.02449475202401": "This is the main idea of this site The",
    "31.38748920765358": "with your main idea  and include the",
    "31.30755790373426": [
      ":",
      " The main idea is that"
    ],
    "31.669736446563473": [
      "What do you think",
      "The main idea :"
    ],
    "30.589457983486263": [
      "The body of",
      "This is the main idea "
    ],
    "31.451962514249498": [
      "Mr",
      "The main idea :"
    ],
    "31.57458043370528": "This is the main idea of this article My",
    "32.47361327408744": "The main idea : What is the",
    "32.34015003516204": [
      ":",
      "The main idea is that"
    ],
    "31.44956188369624": [
      ":",
      " The main idea here is that"
    ],
    "29.90274323506391": [
      "",
      "\"That is the main idea \""
    ],
    "31.017760551645033": [
      ":",
      "The main idea of this story is that"
    ],
    "31.27609011386275": [
      ":",
      "The main idea of the story is that"
    ],
    "32.80510822200094": [
      "Can you help me",
      "The main idea is that"
    ],
    "30.660977033041213": "This is the main idea of this story: The",
    "31.893370046068757": "This is the main idea behind this article The",
    "29.935811838389096": [
      ":",
      " The main idea of this story is that"
    ],
    "30.8996720741549": [
      "",
      "! The main idea is that"
    ],
    "31.9207224163336": " The main idea is that the",
    "29.328181766222297": [
      "James",
      "The main idea of this article is to provide information about the case"
    ],
    "33.08915969265259": "The main idea : What's the",
    "33.124955411625336": "The main idea is that So the",
    "31.21206433059583": [
      "",
      "The main idea of this article is that"
    ],
    "31.91516982685408": "The main idea of this article is that My",
    "33.42632130168371": "The main idea was to save money \"The",
    "33.03842190722436": "Remember the main idea of this article The",
    "30.009050477698274": [
      "",
      "with the main idea :"
    ],
    "28.71515401738827": [
      "",
      ", with the main idea being:"
    ],
    "30.458252767862295": " Your main idea : with the",
    "31.989619077713233": [
      "!",
      "The main idea is the same:"
    ]
  }
}