{
  "0.15426936472235572": [
    ".",
    ": What was the name of your first single and",
    "MAYU WATABE:"
  ],
  "0.1383390410843057": [
    ".",
    ": What was the name of your first single and",
    "MAYU WATANA:"
  ],
  "0.12552182278430482": [
    "Q.:",
    ":",
    "A:"
  ],
  "0.12516838019565535": [
    "Q:",
    "F:",
    "A:"
  ],
  "0.1239732404180075": [
    "DORRIES:",
    "F:",
    "DORRIES:"
  ],
  "0.12321133938942032": [
    "? Q:",
    "F:",
    "A:"
  ],
  "0.12289972002652524": [
    "? QUESTION:",
    "F:",
    "Answer:"
  ],
  "0.12243045221017002": [
    "Q:",
    "K:",
    "A:"
  ],
  "0.11942519823008467": [
    "? Q:",
    ":",
    "A:"
  ],
  "0.11933327619015359": [
    "Q:",
    ":",
    "A:"
  ],
  "0.1177468692007687": [
    ".:",
    "F:",
    "?:"
  ],
  "0.11636832895763104": [
    "? Q:",
    "K:",
    "A:"
  ],
  "0.1140446338659561": [
    ".",
    ":",
    ""
  ],
  "0.11365000124048456": [
    "LESLIE BRODEL:",
    "F:",
    "LESSLIEBRODEL:"
  ],
  "0.11363880906238243": [
    "D:",
    "F:",
    "STILLS:"
  ],
  "0.11357802413191039": [
    ". Q:",
    ":",
    "A:"
  ],
  "0.11309485132014956": [
    ".",
    ":",
    "A:"
  ],
  "0.11233741049286555": [
    "LESLIE BRODEL:",
    "F:",
    "LELIE BRODEL:"
  ],
  "0.11182784738887923": [
    ".",
    "F:",
    "I"
  ],
  "0.10873317182265892": [
    "BRADLEY:",
    "K:",
    "WHERE WAS SHE BORN?:"
  ],
  "0.10761353788846849": [
    ".",
    ":",
    "? I"
  ],
  "0.10760911374237427": [
    "BIOGRAPHY:",
    "K.COM:",
    "ALICE BETH MOORE:"
  ],
  "0.10742210913117081": [
    ".",
    "F:",
    "BELL:"
  ],
  "0.10732189076106738": [
    "? QUESTION:",
    "F:",
    "ASK:"
  ],
  "0.10683149018209268": [
    ".",
    "F:",
    "Answer:"
  ],
  "0.10528561838358143": [
    ".",
    "F:",
    "BROOKS:"
  ],
  "0.10306714521044294": [
    "? A:",
    ":",
    "B:"
  ],
  "0.10302944700741563": [
    ".",
    "F:",
    "JOHNS:"
  ],
  "0.10260695803619757": [
    ".",
    "F:",
    "?"
  ],
  "0.10118436106798186": [
    "DORRIES:",
    "K:",
    "DORRIES:"
  ],
  "0.10038477917250323": [
    ".",
    ":",
    "Yes,"
  ],
  "0.10011862519686253": [
    ".",
    "F:",
    "LEVIN:"
  ],
  "0.10002029135315298": [
    ".",
    ":",
    "Answer:"
  ],
  "0.09987249516687047": [
    ".",
    ":",
    "I"
  ],
  "0.09977456487815774": [
    ".:",
    "K:",
    "?:"
  ],
  "0.09970690287894222": [
    ".",
    "VE:",
    "I"
  ],
  "0.09957940083878819": [
    ".",
    "F:",
    "KEANE:"
  ],
  "0.09945708023934192": [
    ".",
    "F:",
    "ART BELL"
  ],
  "0.09852464110818542": [
    "?",
    ":",
    "I"
  ],
  "0.09842304088591634": [
    ".",
    "VE:",
    "JOHNS:"
  ],
  "0.09816536656055382": [
    ".",
    "K:",
    "JOHNS:"
  ],
  "0.09764821490032256": [
    "D:",
    "DS:",
    "STILLS:"
  ],
  "0.09761750161063505": [
    ".",
    "F:",
    "USHER:"
  ],
  "0.09703116133546567": [
    ".",
    "F:",
    "JOHN PHOENIX:"
  ],
  "0.09687923426600435": [
    ".",
    "F:",
    "CONSTANTIUS:"
  ],
  "0.09597185153344467": [
    "? QUESTION:",
    "K:",
    "ASK:"
  ],
  "0.09587502036148556": [
    ".",
    "F:",
    "JACKSON:"
  ],
  "0.09571553441039407": [
    ".",
    "F:",
    "?:"
  ],
  "0.09563557812505771": [
    "A:",
    "K:",
    "CONSTANTIUS:"
  ],
  "0.09545585228617741": [
    ".",
    ":",
    "JOHNS:"
  ],
  "0.09544707801911914": [
    "D:",
    "DER:",
    "STILLS:"
  ],
  "0.09446778584511269": [
    "? QUESTION:",
    "VE:",
    "ASK:"
  ],
  "0.09445962125732422": [
    "INTRODUCTION:",
    "K:",
    "TIMEBIRICHE:"
  ],
  "0.0944094539416355": [
    ".",
    "F:",
    "DORRIES:"
  ],
  "0.09406249094175172": [
    "INTRODUCTION:",
    "VE:",
    "TIMEBIRICHE:"
  ],
  "0.09401403206552042": [
    ".",
    ":",
    "We"
  ],
  "0.09334398978502674": [
    ".",
    ":",
    "JOHN KEANE"
  ],
  "0.09327224306545774": [
    ".:",
    ":",
    "?:"
  ],
  "0.09320264580521741": [
    ".",
    ":",
    "?:"
  ],
  "0.09273702397733036": [
    ".",
    "VE:",
    "USHER:"
  ],
  "0.09243330038206023": [
    ".",
    ": And",
    "DORRIES "
  ],
  "0.0921929929777207": [
    ".",
    "F:",
    "TIMEBIRICHE:"
  ],
  "0.09217627906237769": [
    ".",
    "K:",
    "BELL:"
  ],
  "0.09199240558880506": [
    ".",
    ":",
    "BELL:"
  ],
  "0.0914551463878819": [
    ".",
    ":",
    "CONSTANTIUS "
  ],
  "0.09020148122648053": [
    ".",
    ":",
    "DORRIES:"
  ],
  "0.08941718219112031": [
    ".",
    "FT:",
    "KEANE:"
  ],
  "0.08856221042291876": [
    ".",
    ":",
    "?"
  ],
  "0.08825745351543235": [
    ". Anna",
    ":",
    "ANNA HAZARE"
  ],
  "0.08778970603154193": [
    ".",
    ":",
    "CONSTANTIUS:"
  ],
  "0.08762552934588412": [
    ".",
    "K:",
    "DORRIES:"
  ],
  "0.0868146845821568": [
    ".",
    "K:",
    "USHER:"
  ],
  "0.0866768572554605": [
    "?:",
    "F:",
    "\"Sparkle?\":"
  ],
  "0.08658126261469523": [
    ".",
    "F:",
    "LESSILIE BRODEL:"
  ],
  "0.08648872366245572": [
    "d.",
    "D:",
    "BOB DYLAN:"
  ],
  "0.08563210819078156": [
    ".",
    "K:",
    "?"
  ],
  "0.0850825481592529": [
    ".",
    "Z:",
    "CONSTANTIUS:"
  ],
  "0.08500490338242683": [
    "355:",
    ":",
    "CONSTANTIUS:"
  ],
  "0.08496673078343475": [
    "?:",
    ":",
    "Cannot answer!:"
  ],
  "0.08477442974806985": [
    ".",
    "F:",
    "LESLIE BRODEL:"
  ],
  "0.08463044643610403": [
    ".",
    "K:",
    "LEVIN:"
  ],
  "0.08460488067417196": [
    ".",
    "VE:",
    "?:"
  ],
  "0.08440291199118304": [
    ".",
    ":",
    "BOONE:"
  ],
  "0.08414214718743632": [
    ".",
    "K:",
    "?:"
  ],
  "0.08370483151955221": [
    ".",
    "K:",
    "CONSTANTIUS:"
  ],
  "0.08360136785995964": [
    "?:",
    ":",
    "Cannot Answer:"
  ],
  "0.08330160531618609": [
    ".",
    ":",
    "Cannot answer:"
  ],
  "0.08304604288268201": [
    ".",
    "K:",
    "Pink:"
  ],
  "0.08294103820514712": [
    ".",
    "F:",
    "DONNIE KLANG:"
  ],
  "0.08253781828623447": [
    ".",
    "K:",
    "TIMEBIRICHE:"
  ],
  "0.0822921068587455": [
    ".",
    "K:",
    "KEANE:"
  ],
  "0.08196461409523195": [
    ".",
    "K:",
    "BOONE:"
  ],
  "0.08016450968268597": [
    ".",
    "K:",
    "BROOKS:"
  ],
  "0.07942881952822053": [
    ".",
    "K:",
    "SORABIJI:"
  ],
  "0.07909563149439394": [
    "?:",
    "VE:",
    "Dylan:"
  ],
  "0.07655974294889763": [
    ".",
    "K:",
    "LESLIE BRODEL:"
  ],
  "0.07574812801781591": [
    ".",
    ":",
    "DONNIE KLANG:"
  ],
  "0.06686233572435471": [
    ".",
    "::",
    "?:"
  ],
  "0.06632270880744977": [
    ".",
    "VE:",
    "DONNIE KLANG:"
  ]
}